simplefin/__init__.py
simplefin/client.py
simplefin/cli/__init__.py
simplefin-0.2.0.dist-info/METADATA
simplefin-0.2.0.dist-info/WHEEL
simplefin-0.2.0.dist-info/entry_points.txt
simplefin-0.2.0.dist-info/licenses/LICENSE
simplefin-0.2.0.dist-info/RECORD
