Metadata-Version: 2.4
Name: simplefin
Version: 0.2.0
Summary: Add your description here
Author-email: Chris Hasenpflug <git@chris.hasenpflug.net>
License-File: LICENSE
Requires-Python: >=3.13
Requires-Dist: click>=8.1.8
Requires-Dist: httpx>=0.28.1
Requires-Dist: rich>=13.9.4
